odoo10_addon_mrp_property-10.0.1.0.0.99.dev4-py3.8-nspkg.pth
odoo/addons/mrp_property/README.rst
odoo/addons/mrp_property/__init__.py
odoo/addons/mrp_property/__manifest__.py
odoo/addons/mrp_property/hooks.py
odoo/addons/mrp_property/i18n/mrp_property.pot
odoo/addons/mrp_property/models/__init__.py
odoo/addons/mrp_property/models/mrp_bom.py
odoo/addons/mrp_property/models/mrp_property.py
odoo/addons/mrp_property/models/mrp_property_group.py
odoo/addons/mrp_property/models/procurement_order.py
odoo/addons/mrp_property/models/sale_order_line.py
odoo/addons/mrp_property/models/stock_move.py
odoo/addons/mrp_property/readme/CONTRIBUTORS.rst
odoo/addons/mrp_property/readme/CREDITS.rst
odoo/addons/mrp_property/readme/DESCRIPTION.rst
odoo/addons/mrp_property/security/ir.model.access.csv
odoo/addons/mrp_property/static/description/icon.png
odoo/addons/mrp_property/static/description/index.html
odoo/addons/mrp_property/tests/__init__.py
odoo/addons/mrp_property/tests/test_mrp_property.py
odoo/addons/mrp_property/views/mrp_bom.xml
odoo/addons/mrp_property/views/mrp_property.xml
odoo/addons/mrp_property/views/mrp_property_group.xml
odoo/addons/mrp_property/views/procurement_order.xml
odoo/addons/mrp_property/views/sale_order.xml
odoo10_addon_mrp_property-10.0.1.0.0.99.dev4.dist-info/METADATA
odoo10_addon_mrp_property-10.0.1.0.0.99.dev4.dist-info/WHEEL
odoo10_addon_mrp_property-10.0.1.0.0.99.dev4.dist-info/namespace_packages.txt
odoo10_addon_mrp_property-10.0.1.0.0.99.dev4.dist-info/top_level.txt
odoo10_addon_mrp_property-10.0.1.0.0.99.dev4.dist-info/RECORD
