Metadata-Version: 2.1
Name: odoo10-addon-mrp-property
Version: 10.0.1.0.0.99.dev4
Summary: Control BoM selection from properties on sale order lines
Home-page: https://github.com/oca/manufacture
Author: Odoo S.A.,Opener B.V.,Odoo Community Association (OCA)
Author-email: support@odoo-community.org
License: LGPL-3
Platform: UNKNOWN
Classifier: Programming Language :: Python
Classifier: Framework :: Odoo
Classifier: Framework :: Odoo :: 10.0
Classifier: License :: OSI Approved :: GNU Lesser General Public License v3 (LGPLv3)
Classifier: Development Status :: 5 - Production/Stable
Requires-Python: ~=2.7
Requires-Dist: odoo <10.1dev,>=10.0
